pytilz/__init__.py
pytilz/fixtures.py
pytilz/py.typed
pytilz-0.1.0.dist-info/METADATA
pytilz-0.1.0.dist-info/WHEEL
pytilz-0.1.0.dist-info/entry_points.txt
pytilz-0.1.0.dist-info/RECORD
