Metadata-Version: 2.1
Name: pytilz
Version: 0.1.0
Summary: 
Author: Ilya Nekhay
Author-email: nekhayiv@gmail.com
Requires-Python: >=3.10,<4.0
Classifier: Programming Language :: Python :: 3
Classifier: Programming Language :: Python :: 3.10
Classifier: Programming Language :: Python :: 3.11
Classifier: Programming Language :: Python :: 3.12
Requires-Dist: respx
